Dossenge/Dossenge.py
Dossenge/__init__.py
Dossenge/arrayable_class.py
Dossenge/http.py
Dossenge/package.py
Dossenge/stdio.py
Dossenge/string.py
dossenge-1.0.post2.dist-info/METADATA
dossenge-1.0.post2.dist-info/WHEEL
dossenge-1.0.post2.dist-info/entry_points.txt
dossenge-1.0.post2.dist-info/top_level.txt
dossenge-1.0.post2.dist-info/RECORD
