Metadata-Version: 2.1
Name: dossenge
Version: 1.0.post2
Summary: Dossenge 1.0.post2 紧急修复
Home-page: http://github.com/Dossenge/Dossenge.git
Author: Dossenge
Requires-Python: >=3.5
Requires-Dist: toml
Requires-Dist: requests
